stable_pretraining/__about__.py
stable_pretraining/__init__.py
stable_pretraining/_version.py
stable_pretraining/cli.py
stable_pretraining/config.py
stable_pretraining/forward.py
stable_pretraining/manager.py
stable_pretraining/module.py
stable_pretraining/run.py
stable_pretraining/static.py
stable_pretraining/backbone/__init__.py
stable_pretraining/backbone/aggregator.py
stable_pretraining/backbone/convmixer.py
stable_pretraining/backbone/mae.py
stable_pretraining/backbone/mlp.py
stable_pretraining/backbone/probe.py
stable_pretraining/backbone/resnet9.py
stable_pretraining/backbone/utils.py
stable_pretraining/backbone/vit.py
stable_pretraining/callbacks/__init__.py
stable_pretraining/callbacks/checkpoint_sklearn.py
stable_pretraining/callbacks/cleanup.py
stable_pretraining/callbacks/clip_zero_shot.py
stable_pretraining/callbacks/cpu_offload.py
stable_pretraining/callbacks/earlystop.py
stable_pretraining/callbacks/embedding_cache.py
stable_pretraining/callbacks/env_info.py
stable_pretraining/callbacks/factories.py
stable_pretraining/callbacks/image_retrieval.py
stable_pretraining/callbacks/knn.py
stable_pretraining/callbacks/latent_viz.py
stable_pretraining/callbacks/lidar.py
stable_pretraining/callbacks/probe.py
stable_pretraining/callbacks/queue.py
stable_pretraining/callbacks/rankme.py
stable_pretraining/callbacks/registry.py
stable_pretraining/callbacks/teacher_student.py
stable_pretraining/callbacks/trainer_info.py
stable_pretraining/callbacks/utils.py
stable_pretraining/callbacks/wd_schedule.py
stable_pretraining/callbacks/writer.py
stable_pretraining/data/__init__.py
stable_pretraining/data/collate.py
stable_pretraining/data/dataset_stats.py
stable_pretraining/data/datasets.py
stable_pretraining/data/download.py
stable_pretraining/data/masking.py
stable_pretraining/data/module.py
stable_pretraining/data/sampler.py
stable_pretraining/data/synthetic_data.py
stable_pretraining/data/transforms.py
stable_pretraining/data/utils.py
stable_pretraining-0.1.5.dist-info/licenses/LICENSE
stable_pretraining-0.1.5.dist-info/METADATA
stable_pretraining-0.1.5.dist-info/WHEEL
stable_pretraining-0.1.5.dist-info/entry_points.txt
stable_pretraining-0.1.5.dist-info/top_level.txt
stable_pretraining-0.1.5.dist-info/RECORD
