Metadata-Version: 2.4
Name: stable-pretraining
Version: 0.1.5
Summary: Stable Pretraining Library for Self-Supervised Learning
License: MIT
License-File: LICENSE
Requires-Dist: torch
Requires-Dist: torchvision
Requires-Dist: torchmetrics
Requires-Dist: lightning
Requires-Dist: hydra-core
Requires-Dist: omegaconf
Requires-Dist: loguru
Requires-Dist: tabulate
Requires-Dist: pandas
Requires-Dist: rich
Requires-Dist: requests-cache
Requires-Dist: prettytable
Requires-Dist: submitit
Requires-Dist: timm
Requires-Dist: zstandard
Requires-Dist: typer
Requires-Dist: transformers
Requires-Dist: pillow>=11.3.0
Requires-Dist: wandb
Requires-Dist: hydra-submitit-launcher
Requires-Dist: matplotlib
Requires-Dist: datasets
Requires-Dist: pyarrow==20.0.0
Requires-Dist: minari[hdf5]>=0.5.3
Requires-Dist: scikit-learn>=1.7.0
Requires-Dist: richuru
Provides-Extra: dev
Requires-Dist: pytest; extra == "dev"
Requires-Dist: coverage; extra == "dev"
Requires-Dist: pytest-cov; extra == "dev"
Requires-Dist: codecov; extra == "dev"
Requires-Dist: pre-commit; extra == "dev"
Requires-Dist: ruff; extra == "dev"
Requires-Dist: sphinx; extra == "dev"
Requires-Dist: sphinx-gallery; extra == "dev"
Requires-Dist: sphinx-book-theme; extra == "dev"
Requires-Dist: sphinxcontrib-bibtex; extra == "dev"
Requires-Dist: matplotlib; extra == "dev"
Requires-Dist: memory_profiler; extra == "dev"
Requires-Dist: myst-parser; extra == "dev"
Dynamic: license-file
